flask_orphus/__init__.py
flask_orphus/auth/__init__.py
flask_orphus/core/Container.py
flask_orphus/core/Provider.py
flask_orphus/core/__init__.py
flask_orphus/event/__init__.py
flask_orphus/event/examples.py
flask_orphus/event/fire_starter.py
flask_orphus/helpers/__init__.py
flask_orphus/helpers/ns/__init__.py
flask_orphus/helpers/str/__init__.py
flask_orphus/http/__init__.py
flask_orphus/http/flask_requester.py
flask_orphus/logging/__init__.py
flask_orphus/logging/log.py
flask_orphus/routing/__init__.py
flask_orphus/routing/content_collection/__init__.py
flask_orphus/routing/fs_router/__init__.py
flask_orphus/routing/fs_router/fs_router.py
flask_orphus/routing/fs_router_api/__init__.py
flask_orphus/routing/fs_router_api/flask_router_api.py
flask_orphus/routing/micro/__init__.py
flask_orphus/routing/micro/css_isolate.py
flask_orphus/routing/micro/micro.py
flask_orphus/stubs/.env
flask_orphus/stubs/logout.py
flask_orphus/stubs/requirements.txt
flask_orphus/validation/__init__.py
flask_orphus/validation/rules.py
flask_orphus-0.1.8.dist-info/METADATA
flask_orphus-0.1.8.dist-info/WHEEL
flask_orphus-0.1.8.dist-info/top_level.txt
flask_orphus-0.1.8.dist-info/RECORD
