Metadata-Version: 2.1
Name: flask-orphus
Version: 0.1.8
Summary: A package that extends the flask webframework in a very opinionated way.
Home-page: https://github.com/JarriqTheTechie/flask_orphus
Author: Jarriq Rolle
Author-email: jrolle@bnbbahamas.com
Classifier: Programming Language :: Python :: 3
Classifier: License :: OSI Approved :: MIT License
Classifier: Operating System :: OS Independent
Requires-Python: >=3.9
Requires-Dist: flask
Requires-Dist: python-dotenv
Requires-Dist: masonite-orm
